{
  "id": "investimentos-appbar_20260603",
  "title": "Refactor — InvestimentosPage para SharedAppBar",
  "type": "refactor",
  "status": "complete",
  "created": "2026-06-03T00:00:00.000Z",
  "updated": "2026-06-03T00:00:00.000Z",
  "phases": {
    "total": 2,
    "completed": 2
  },
  "tasks": {
    "total": 7,
    "completed": 7
  },
  "commits": [
    "41cb519: refactor(investimentos): migra InvestimentosPage para SharedAppBar",
    "7ac5071: refactor(investimentos): remove OrcamentosAppBar sem consumidores"
  ]
}
